mlpype/fastapi/__init__.py
mlpype/fastapi/deploy/__init__.py
mlpype/fastapi/deploy/app.py
mlpype/fastapi/deploy/wheel_extension.py
mlpype/fastapi/deploy/wheel/helpers.py
mlpype_fastapi-0.6.12.dist-info/METADATA
mlpype_fastapi-0.6.12.dist-info/WHEEL
mlpype_fastapi-0.6.12.dist-info/RECORD
