Metadata-Version: 2.4
Name: mlpype-fastapi
Version: 0.6.12
Summary: FastAPI extension for MLpype
Author: Jeroen van den Hoven
License: MIT
Requires-Python: >=3.9
Requires-Dist: anyio<4
Requires-Dist: fastapi>=0.86.0
Requires-Dist: mlpype-base
Requires-Dist: typing-extensions>=4.8.0
Provides-Extra: dev
Requires-Dist: uvicorn==0.18.2; extra == 'dev'
Provides-Extra: strict
Requires-Dist: anyio<4; extra == 'strict'
Requires-Dist: fastapi==0.86.0; extra == 'strict'
Requires-Dist: typing-extensions==4.8.0; extra == 'strict'
